{
  "kind": "collectionType",
  "collectionName": "blog_posts",
  "info": {
    "singularName": "blog-post",
    "pluralName": "blog-posts",
    "displayName": "Blog Post",
    "description": "Blog articles for BabyVision ecosystem"
  },
  "options": {
    "draftAndPublish": true
  },
  "pluginOptions": {},
  "attributes": {
    "title": {
      "type": "string",
      "required": true,
      "maxLength": 255
    },
    "slug": {
      "type": "uid",
      "targetField": "title",
      "required": true
    },
    "content": {
      "type": "blocks",
      "required": true
    },
    "thumbnail": {
      "type": "media",
      "multiple": false,
      "required": false,
      "allowedTypes": ["images"]
    },
    "author": {
      "type": "relation",
      "relation": "manyToOne",
      "target": "plugin::users-permissions.user",
      "inversedBy": "blog_posts"
    },
    "excerpt": {
      "type": "text",
      "maxLength": 500
    },
    "categories": {
      "type": "relation",
      "relation": "manyToMany",
      "target": "api::category.category",
      "inversedBy": "blog_posts"
    },
    "featured": {
      "type": "boolean",
      "default": false
    },
    "seo_title": {
      "type": "string",
      "maxLength": 60
    },
    "seo_description": {
      "type": "string",
      "maxLength": 160
    }
  }
}
